mcp_server_qq_music/__init__.py
mcp_server_qq_music/__main__.py
mcp_server_qq_music/browser.py
mcp_server_qq_music/server.py
mcp_server_qq_music/settings.py
mcp_server_qq_music-0.1.4.dist-info/METADATA
mcp_server_qq_music-0.1.4.dist-info/WHEEL
mcp_server_qq_music-0.1.4.dist-info/entry_points.txt
mcp_server_qq_music-0.1.4.dist-info/RECORD
