Metadata-Version: 2.4
Name: mcp-server-qq-music
Version: 0.1.4
Summary: QQ Music MCP Server
Author-email: saltfishpr <saltfishpr@gmail.com>
License-Expression: MIT
Requires-Python: >=3.13
Requires-Dist: fastmcp>=2.2.1
Requires-Dist: mcp-server-lib
Requires-Dist: mcp[cli]>=1.0.0
Requires-Dist: playwright>=1.51.0
Requires-Dist: pydantic>=2.0.0
